llama_index/llms/ai21/__init__.py
llama_index/llms/ai21/base.py
llama_index/llms/ai21/utils.py
llama_index_llms_ai21-0.6.1.dist-info/METADATA
llama_index_llms_ai21-0.6.1.dist-info/WHEEL
llama_index_llms_ai21-0.6.1.dist-info/licenses/LICENSE
llama_index_llms_ai21-0.6.1.dist-info/RECORD
