Metadata-Version: 2.4
Name: llama-index-llms-ai21
Version: 0.6.1
Summary: llama-index llms ai21 integration
Author-email: Your Name <you@example.com>
License-Expression: MIT
License-File: LICENSE
Requires-Python: <4.0,>=3.9
Requires-Dist: ai21<3,>=2.13.0
Requires-Dist: llama-index-core<0.15,>=0.13.0
